README.rst
setup.py
mtirc/__init__.py
mtirc/bot.py
mtirc/cache.py
mtirc/pinger.py
mtirc/settings.py
mtirc.egg-info/PKG-INFO
mtirc.egg-info/SOURCES.txt
mtirc.egg-info/dependency_links.txt
mtirc.egg-info/requires.txt
mtirc.egg-info/top_level.txt