Metadata-Version: 1.1
Name: mtirc
Version: 0.2.0
Summary: A fully functioning multi-threaded IRC client.
Home-page: http://github.com/legoktm/mtirc/
Author: Kunal Mehta
Author-email: legoktm@gmail.com
License: MIT License
Platform: UNKNOWN
Classifier: Programming Language :: Python
Classifier: Programming Language :: Python :: 2
Classifier: Development Status :: 2 - Pre-Alpha
Classifier: Intended Audience :: Developers
Classifier: Operating System :: OS Independent
